devodsconnector/__init__.py
devodsconnector/__version__.py
devodsconnector/error_checking.py
devodsconnector/json_writer.py
devodsconnector/reader.py
devodsconnector/writer.py
devodsconnector-3.0.2.dist-info/LICENSE
devodsconnector-3.0.2.dist-info/METADATA
devodsconnector-3.0.2.dist-info/WHEEL
devodsconnector-3.0.2.dist-info/top_level.txt
devodsconnector-3.0.2.dist-info/RECORD
