Metadata-Version: 2.1
Name: devodsconnector
Version: 3.0.2
Summary: APIs for querying and loading data into Devo
Home-page: https://github.com/DevoInc/python-ds-connector
Author: Nick Murphy
Author-email: nick.murphy@devo.com
License: MIT
Platform: UNKNOWN
Classifier: License :: OSI Approved :: MIT License
Requires-Python: >=3.5
Requires-Dist: numpy (>=1.15.1)
Requires-Dist: pandas (>=0.23.4)
Requires-Dist: requests (>=2.19.1)
Requires-Dist: scipy (>=1.1.0)
Requires-Dist: devo-sdk (>=3.4.1)
